napari_toolkit/__init__.py
napari_toolkit/widget_gallery.py
napari_toolkit/_tests/__init__.py
napari_toolkit/_tests/test_widget_setup.py
napari_toolkit/_tests/test_widget_values.py
napari_toolkit/containers/__init__.py
napari_toolkit/containers/boxlayout.py
napari_toolkit/containers/collapsible_groupbox.py
napari_toolkit/containers/groupbox.py
napari_toolkit/containers/scroll_area.py
napari_toolkit/containers/tab_widget.py
napari_toolkit/data_structs/__init__.py
napari_toolkit/data_structs/list.py
napari_toolkit/data_structs/table.py
napari_toolkit/data_structs/tree.py
napari_toolkit/resources/DKFZ_Logo.png
napari_toolkit/resources/HI_Logo.png
napari_toolkit/utils/__init__.py
napari_toolkit/utils/theme.py
napari_toolkit/utils/utils.py
napari_toolkit/utils/widget_getter.py
napari_toolkit/utils/widget_setter.py
napari_toolkit/widgets/__init__.py
napari_toolkit/widgets/acknowledgements.py
napari_toolkit/widgets/checkbox.py
napari_toolkit/widgets/combobox.py
napari_toolkit/widgets/file_select.py
napari_toolkit/widgets/icon_wrapper.py
napari_toolkit/widgets/layer_select.py
napari_toolkit/widgets/spinbox.py
napari_toolkit/widgets/switch.py
napari_toolkit/widgets/text_edit.py
napari_toolkit/widgets/timeedit.py
napari_toolkit/widgets/buttons/__init__.py
napari_toolkit/widgets/buttons/icon_button.py
napari_toolkit/widgets/buttons/push_button.py
napari_toolkit/widgets/buttons/radio_button.py
napari_toolkit/widgets/buttons/toggle_button.py
napari_toolkit/widgets/buttons/tool_button.py
napari_toolkit/widgets/color/__init__.py
napari_toolkit/widgets/color/color_picker.py
napari_toolkit/widgets/color/colorbar.py
napari_toolkit/widgets/color/edit_color_picker.py
napari_toolkit/widgets/progressbar/__init__.py
napari_toolkit/widgets/progressbar/progress_edit.py
napari_toolkit/widgets/progressbar/progressbar.py
napari_toolkit/widgets/sliders/__init__.py
napari_toolkit/widgets/sliders/double_slider.py
napari_toolkit/widgets/sliders/edit_slider.py
napari_toolkit-0.0.9.dist-info/licenses/LICENSE
napari_toolkit-0.0.9.dist-info/METADATA
napari_toolkit-0.0.9.dist-info/WHEEL
napari_toolkit-0.0.9.dist-info/top_level.txt
napari_toolkit-0.0.9.dist-info/RECORD
