Metadata-Version: 2.4
Name: napari_toolkit
Version: 0.0.9
Summary: Toolkit to handle  QWidgets for Napari Plugins.
Author: Lars Krämer
Author-email: lars.kraemer@dkfz-heidelberg.de
License: 
Project-URL: Homepage, https://github.com/MIC-DKFZ/napari_toolkit
Classifier: Development Status :: 2 - Pre-Alpha
Classifier: Framework :: napari
Classifier: Intended Audience :: Developers
Classifier: License :: OSI Approved :: Apache Software License
Classifier: Operating System :: OS Independent
Classifier: Programming Language :: Python
Classifier: Programming Language :: Python :: 3
Classifier: Programming Language :: Python :: 3 :: Only
Classifier: Programming Language :: Python :: 3.9
Classifier: Programming Language :: Python :: 3.10
Classifier: Programming Language :: Python :: 3.11
Classifier: Programming Language :: Python :: 3.12
Classifier: Topic :: Scientific/Engineering :: Image Processing
Requires-Python: >=3.9
License-File: LICENSE
Requires-Dist: numpy
Requires-Dist: qtpy
Requires-Dist: matplotlib
Provides-Extra: testing
Requires-Dist: tox; extra == "testing"
Requires-Dist: pytest; extra == "testing"
Requires-Dist: pytest-cov; extra == "testing"
Requires-Dist: pytest-qt; extra == "testing"
Requires-Dist: PyQt5; extra == "testing"
Requires-Dist: napari; extra == "testing"
Dynamic: license-file
